flame_dash/__init__.py
flame_dash/apphrr.py
flame_dash/appl.py
flame_dash/bar.py
flame_dash/double.py
flame_dash/hcci.py
flame_dash/isml.py
flame_dash/template.py
flame_dash_c-1.0.0.dist-info/LICENSE.txt
flame_dash_c-1.0.0.dist-info/METADATA
flame_dash_c-1.0.0.dist-info/WHEEL
flame_dash_c-1.0.0.dist-info/top_level.txt
flame_dash_c-1.0.0.dist-info/RECORD
